{
  "items": [
    {
      "id": "auto-translation-completed",
      "title": "Bachata Paradox Translation Project Shines!",
      "content": "The Bachata Paradox auto translation project is a fantastic achievement! With support for 29 languages—including Japanese and Chinese—our research paper and the entire site are now accessible to readers around the world. We are committed to making knowledge truly global, and will continue to improve and refine our auto-translated content to ensure the highest quality for all users.",
      "date": "2025-04-15",
      "badge": "new"
    }
   
  ]
}
